.gitignore
LICENSE
README.md
blog.md
demo-vae.py
demo.py
demo2.py
demo4.py
pyproject.toml
setup.py
uv.lock
.github/workflows/release.yml
src/overmind/__init__.py
src/overmind/_version.py
src/overmind/api.py
src/overmind/cli.py
src/overmind/common.py
src/overmind/reducer.py
src/overmind/server.py
src/overmind/shmem.py
src/overmind/assets/__init__.py
src/overmind/assets/predefined.cfg
src/overmind/csrc/omhelpers.cpp
src/overmind/utils/__init__.py
src/overmind/utils/escapes.py
src/overmind/utils/log.py
src/overmind/utils/misc.py
src/overmind/utils/win32mutex.py
src/overmind_cache.egg-info/PKG-INFO
src/overmind_cache.egg-info/SOURCES.txt
src/overmind_cache.egg-info/dependency_links.txt
src/overmind_cache.egg-info/entry_points.txt
src/overmind_cache.egg-info/requires.txt
src/overmind_cache.egg-info/top_level.txt
tests/__init__.py
tests/test_cext.py
tests/test_shmem.py