Metadata-Version: 2.4
Name: overmind-cache
Version: 1.1.2
Summary: Daemon to serve shared PyTorch models
Author-email: Proton <feisuzhu@163.com>
License-Expression: Apache-2.0
Requires-Python: <3.13.0,>3.9.0
License-File: LICENSE
Requires-Dist: daemonize>=2.5.0
Requires-Dist: torch<3.0.0,>=2.3.0
Requires-Dist: dill
Dynamic: license-file
